adapter/Secret_example.py
adapter/__init__.py
adapter/i_o.py
adapter/label_map.py
adapter/to_python.py
adapter/comm/__init__.py
adapter/comm/excel.py
adapter/comm/sql.py
adapter/comm/tools.py
adapterio-1.8.0.dist-info/METADATA
adapterio-1.8.0.dist-info/WHEEL
adapterio-1.8.0.dist-info/top_level.txt
adapterio-1.8.0.dist-info/RECORD
