Metadata-Version: 2.1
Name: adapterio
Version: 1.8.0
Summary: I/O module
Home-page: https://github.com/LBNL-ETA/Adapter
Author: Milica Grahovac, Youness Bennani, Thomas Burke, Katie Coughlin, Mohan Ganeshalingam, Akhil Mathur, Evan Neill, Akshay Sharma, Zheng He and Lyra Lan
License: BSD-3-Clause-LBNL
Keywords: data,tables,IO for research computation,sql,excel,csv,dataframe,connection
Classifier: Programming Language :: Python :: 3.8
Requires-Dist: pandas>=2.2.0
Requires-Dist: xlwings>=0.19.4
Requires-Dist: psycopg2-binary>=2.8.6
Requires-Dist: SQLAlchemy>=2.0.0
Requires-Dist: openpyxl>=3.1.2
